spatch/__init__.py
spatch-0.0.0.dist-info/LICENSE
spatch-0.0.0.dist-info/METADATA
spatch-0.0.0.dist-info/WHEEL
spatch-0.0.0.dist-info/top_level.txt
spatch-0.0.0.dist-info/RECORD
