Metadata-Version: 2.1
Name: spatch
Version: 0.0.0
Summary: Coming soon
Author-email: Jarrod Millman <millman@berkeley.edu>
License-File: LICENSE
